shipyard_http/__init__.py
shipyard_http/cli/__init__.py
shipyard_http/cli/download_file.py
shipyard_http/cli/execute_request.py
shipyard_http-0.2.0.dist-info/METADATA
shipyard_http-0.2.0.dist-info/WHEEL
shipyard_http-0.2.0.dist-info/top_level.txt
shipyard_http-0.2.0.dist-info/RECORD
