Metadata-Version: 2.4
Name: shipyard-http
Version: 0.2.0
Requires-Python: >=3.11
Requires-Dist: requests>=2.32.3
Requires-Dist: shipyard-bp-utils>=1.2.1
Requires-Dist: shipyard-templates>=0.9.0
